[{"id":4,"name":"Charmander","type":["Fire"],"level":5,"xp":0,"xpThreshold":125,"stats":{"HP":17,"Attack":8,"Defense":9,"Sp. Attack":8,"Sp. Defense":9,"Speed":9},"iv":{"HP":17,"Attack":8,"Defense":9,"Sp. Attack":8,"Sp. Defense":9,"Speed":9},"currentHp":17,"evolutionLvl":16,"evolutionId":5,"abilities":[{"id":545,"ename":"Searing Shot","category":"special","type":"Fire","accuracy":100,"power":100,"pp":5},{"id":126,"ename":"Fire Blast","category":"special","type":"Fire","accuracy":85,"power":110,"pp":5},{"id":394,"ename":"Flare Blitz","category":"physic","type":"Fire","accuracy":100,"power":120,"pp":15}]}]